[{"__type__":"cc.SpriteFrame","content":{"name":"b2","texture":"9bcjvIpOBOcraNRqSpa3pE","rect":[0,0,208,219],"offset":[0,0],"originalSize":[208,219],"capInsets":[0,0,0,0]}},{"__type__":"cc.SpriteFrame","content":{"name":"b1","texture":"7epKlEmipCc7AM8lOCIdgj","rect":[0,0,208,204],"offset":[0,0],"originalSize":[208,204],"capInsets":[0,0,0,0]}},{"__type__":"cc.SpriteFrame","content":{"name":"b4","texture":"04cYiMWQpPKbBivNBVXDEA","rect":[0,0,253,237],"offset":[0,0],"originalSize":[253,237],"capInsets":[0,0,0,0]}},{"__type__":"cc.SpriteFrame","content":{"name":"b3","texture":"f4wxqaouZF9o+FmvMvjoNP","rect":[0,0,253,244],"offset":[0,0],"originalSize":[253,244],"capInsets":[0,0,0,0]}},{"__type__":"cc.SpriteFrame","content":{"name":"b5","texture":"6c0PFUwttG0ZTKdOXGZCUx","rect":[0,0,175,265],"offset":[0,0],"originalSize":[175,265],"capInsets":[0,0,0,0]}},{"__type__":"cc.SpriteFrame","content":{"name":"b6","texture":"ceFBoenpxBTbg7rYXIMNLJ","rect":[0,0,178,265],"offset":[0,0],"originalSize":[178,265],"capInsets":[0,0,0,0]}},{"__type__":"cc.AnimationClip","_name":"blast","_duration":1,"sample":20,"curveData":{"props":{"scaleX":[{"frame":0,"value":0.1,"curve":"cubicOut"},{"frame":0.05,"value":1}],"scaleY":[{"frame":0,"value":0.1,"curve":"cubicOut"},{"frame":0.05,"value":1}],"opacity":[{"frame":0.7,"value":254.30000000000004},{"frame":1,"value":0}]},"comps":{"cc.Sprite":{"spriteFrame":[{"frame":0,"value":{"__uuid__":"2fterH7xZMq6FPrpfpB6Nx"}},{"frame":0.1,"value":{"__uuid__":"08dGXe6khMjIN42vLoXfP6"}},{"frame":0.25,"value":{"__uuid__":"70xPTqaa9DYK7f4h7+aEmd"}},{"frame":0.4,"value":{"__uuid__":"59jra1j2pEuZq8I2dbv0mD"}},{"frame":0.55,"value":{"__uuid__":"842dFJejFL/arHRqZMMKbs"}},{"frame":0.7,"value":{"__uuid__":"90DWLnfF5DOpMsgQ8iL3kT"}}]}}}}]